pyos_sphinx_theme/__init__.py
pyos_sphinx_theme/assets/scripts/.gitkeep
pyos_sphinx_theme/assets/styles/abstract/_variables.scss
pyos_sphinx_theme/assets/styles/base/_base.scss
pyos_sphinx_theme/assets/styles/base/_typography.scss
pyos_sphinx_theme/assets/styles/components/_card.scss
pyos_sphinx_theme/assets/styles/components/_icons.scss
pyos_sphinx_theme/assets/styles/components/_navbar.scss
pyos_sphinx_theme/assets/styles/components/_sidebar.scss
pyos_sphinx_theme/assets/styles/contents/_admonitions.scss
pyos_sphinx_theme/assets/styles/contents/_footnotes.scss
pyos_sphinx_theme/assets/styles/contents/_tables.scss
pyos_sphinx_theme/assets/styles/fonts/_fonts.scss
pyos_sphinx_theme/assets/styles/fonts/itim-v14-latin-regular.woff2
pyos_sphinx_theme/assets/styles/fonts/poppins-v20-latin-500.woff2
pyos_sphinx_theme/assets/styles/fonts/poppins-v20-latin-600.woff2
pyos_sphinx_theme/assets/styles/fonts/poppins-v20-latin-700.woff2
pyos_sphinx_theme/assets/styles/fonts/poppins-v20-latin-700italic.woff2
pyos_sphinx_theme/assets/styles/fonts/poppins-v20-latin-italic.woff2
pyos_sphinx_theme/assets/styles/fonts/poppins-v20-latin-regular.woff2
pyos_sphinx_theme/assets/styles/pages/_lesson.scss
pyos_sphinx_theme/assets/styles/pages/_tutorial.scss
pyos_sphinx_theme/assets/styles/pyos-sphinx-theme.scss
pyos_sphinx_theme/assets/styles/sections/_container.scss
pyos_sphinx_theme/assets/styles/vendor/_reboot.scss
pyos_sphinx_theme/html2dirhtml.py
pyos_sphinx_theme/theme/pyos_sphinx_theme/static/images/logo-dark-mode.png
pyos_sphinx_theme/theme/pyos_sphinx_theme/static/images/logo-light-mode.png
pyos_sphinx_theme/theme/pyos_sphinx_theme/static/images/pyopensci-logo-package-guide.png
pyos_sphinx_theme/theme/pyos_sphinx_theme/static/images/pyopensci-python-package-guide.png
pyos_sphinx_theme/theme/pyos_sphinx_theme/static/scripts/matomo.js
pyos_sphinx_theme/theme/pyos_sphinx_theme/static/styles/.gitignore
pyos_sphinx_theme/theme/pyos_sphinx_theme/static/styles/pyos-sphinx-theme.css
pyos_sphinx_theme-0.3.dist-info/LICENSE
pyos_sphinx_theme-0.3.dist-info/METADATA
pyos_sphinx_theme-0.3.dist-info/WHEEL
pyos_sphinx_theme-0.3.dist-info/entry_points.txt
pyos_sphinx_theme-0.3.dist-info/RECORD