Metadata-Version: 2.1
Name: pyos-sphinx-theme
Version: 0.3
Summary: PyOS Documentation Theme.
Author-Email: pyOpenSci Community <pyopensci@pyopensci.org>
Maintainer-Email: pyOpenSci <pyopensci@pyopensci.org>
License: BSD 3-Clause License
Classifier: Framework :: Sphinx
Classifier: Framework :: Sphinx :: Theme
Classifier: License :: OSI Approved :: MIT License
Classifier: Environment :: Web Environment
Classifier: Intended Audience :: Developers
Classifier: Programming Language :: Python :: 3
Classifier: Programming Language :: Python :: 3.10
Classifier: Programming Language :: Python :: 3.11
Classifier: Operating System :: OS Independent
Classifier: Topic :: Documentation
Classifier: Topic :: Software Development :: Documentation
Requires-Python: >=3.9
Requires-Dist: pydata-sphinx-theme==0.16.0
Requires-Dist: sphinx
Requires-Dist: myst_nb
Requires-Dist: sphinxext-opengraph
Requires-Dist: sphinx-copybutton
Requires-Dist: sphinx-togglebutton
Requires-Dist: sphinxext-opengraph>=0.8.0
Requires-Dist: sphinx_design
Requires-Dist: sphinx_sitemap
Provides-Extra: dev
Requires-Dist: sphinx-theme-builder[cli]>=0.2.0a7; extra == "dev"
Provides-Extra: docs
Requires-Dist: myst-parser; extra == "docs"
Requires-Dist: IPython; extra == "docs"
